n_bit_binary/__init__.py
n_bit_binary/n_bit_binary.py
n_bit_binary-0.1.1.dist-info/METADATA
n_bit_binary-0.1.1.dist-info/WHEEL
n_bit_binary-0.1.1.dist-info/licenses/LICENSE
n_bit_binary-0.1.1.dist-info/RECORD
